openjury/__init__.py
openjury/config.py
openjury/env.py
openjury/juror.py
openjury/jury_engine.py
openjury/logger.py
openjury/output_format.py
openjury/prompt_templates.py
openjury/voting.py
openjury-0.1.0.dist-info/METADATA
openjury-0.1.0.dist-info/WHEEL
openjury-0.1.0.dist-info/licenses/LICENSE
openjury-0.1.0.dist-info/RECORD
