Metadata-Version: 2.4
Name: openjury
Version: 0.1.0
Summary: Python SDK for evaluating multiple model outputs using configurable LLM-based jurors
Project-URL: Homepage, https://github.com/robiscoding/openjury
Project-URL: Repository, https://github.com/robiscoding/openjury
Project-URL: Issues, https://github.com/robiscoding/openjury/issues
Author-email: robiscoding <robiscodingg@gmail.com>
License: Apache-2.0
License-File: LICENSE
Keywords: ai,evaluation,langchain,llm,llm-as-a-judge,machine-learning,model-comparison,model-consensus,openai
Classifier: Development Status :: 3 - Alpha
Classifier: Intended Audience :: Developers
Classifier: License :: OSI Approved :: Apache Software License
Classifier: Programming Language :: Python :: 3
Classifier: Programming Language :: Python :: 3.11
Classifier: Programming Language :: Python :: 3.12
Requires-Python: >=3.11
Requires-Dist: langchain-openai>=0.1.0
Requires-Dist: langchain>=0.1.0
Requires-Dist: openai>=1.0.0
Requires-Dist: pydantic>=2.0.0
Provides-Extra: dev
Requires-Dist: black>=23.0.0; extra == 'dev'
Requires-Dist: isort>=5.12.0; extra == 'dev'
Requires-Dist: mypy>=1.0.0; extra == 'dev'
Requires-Dist: pytest-cov>=4.0.0; extra == 'dev'
Requires-Dist: pytest>=7.0.0; extra == 'dev'
Requires-Dist: twine>=4.0.0; extra == 'dev'
